{
    "version": "4.1.0",
    "objects": [{
        "type": "rect",
        "version": "4.1.0",
        "originX": "center",
        "originY": "center",
        "left": 500,
        "top": 500,
        "width": 200,
        "height": 340,
        "fill": "rgb(37,53,73)",
        "stroke": null,
        "strokeWidth": 1,
        "strokeDashArray": null,
        "strokeLineCap": "butt",
        "strokeDashOffset": 0,
        "strokeLineJoin": "miter",
        "strokeMiterLimit": 4,
        "scaleX": 1,
        "scaleY": 1,
        "angle": 0,
        "flipX": false,
        "flipY": false,
        "opacity": 1,
        "shadow": null,
        "visible": true,
        "backgroundColor": "",
        "fillRule": "nonzero",
        "paintFirst": "fill",
        "globalCompositeOperation": "source-over",
        "skewX": 0,
        "skewY": 0,
        "rx": 0,
        "ry": 0
    }]
}